streamlit_layoutr/__init__.py
streamlit_layoutr/example.py
streamlit_layoutr/frontend/dist/index.html
streamlit_layoutr/frontend/dist/assets/index-IMNa3Qvg.js
streamlit_layoutr/frontend/dist/assets/index-kPhQrrKW.js
streamlit_layoutr/frontend/dist/assets/index-w2Z2udi6.css
streamlit_layoutr/frontend/dist/assets/index-ymqg9Qw9.js
streamlit_layoutr/frontend/dist/assets/worker-UepSgFYo.js
streamlit_layoutr-0.0.3.dist-info/LICENSE
streamlit_layoutr-0.0.3.dist-info/METADATA
streamlit_layoutr-0.0.3.dist-info/WHEEL
streamlit_layoutr-0.0.3.dist-info/top_level.txt
streamlit_layoutr-0.0.3.dist-info/RECORD
