Metadata-Version: 2.1
Name: streamlit-layoutr
Version: 0.0.3
Summary: Streamlit component for graph visualization
Home-page: https://github.com/kitware/layoutr
Author: Kitware
Author-email: kitware@kitware.com
License: UNKNOWN
Platform: UNKNOWN
Requires-Python: >=3.7
License-File: LICENSE
Requires-Dist: streamlit (>=0.63)
